sanic_jinja2/__init__.py
sanic_jinja2-2022.11.11.dist-info/LICENSE.txt
sanic_jinja2-2022.11.11.dist-info/METADATA
sanic_jinja2-2022.11.11.dist-info/WHEEL
sanic_jinja2-2022.11.11.dist-info/top_level.txt
sanic_jinja2-2022.11.11.dist-info/RECORD
