Metadata-Version: 2.1
Name: sanic-jinja2
Version: 2022.11.11
Summary: Jinja2 support for sanic
Home-page: https://github.com/lixxu/sanic-jinja2
Author: Lix Xu
Author-email: xuzenglin@gmail.com
License: bsd-3-clause
Platform: any
Classifier: Environment :: Web Environment
Classifier: Intended Audience :: Developers
Classifier: License :: OSI Approved :: BSD License
Classifier: Operating System :: OS Independent
Classifier: Programming Language :: Python
Classifier: Topic :: Internet :: WWW/HTTP :: Dynamic Content
Classifier: Topic :: Software Development :: Libraries :: Python Modules
Classifier: Programming Language :: Python :: 3
Requires-Python: >=3.7
License-File: LICENSE.txt
